<?xml version="1.0"?>
<partition guid="95B3F566-D66D-11DD-B2D2-FFD259169149" primaryInstance="95B3A744-D66D-11DD-B2D2-FFD259169149" exportMode="All">
	<instance guid="95B3A744-D66D-11DD-B2D2-FFD259169149" type="Render.RigidMeshAsset" id="BarrierSandbagLowCorner_1_Mesh">
		<field name="Name">Objects/Objects/BarrierSandbagLowCorner_1/BarrierSandbagLowCorner_1_Mesh</field>
		<field name="MemoryReportGroup">MemoryReportGroup_default</field>
		<field name="SourceFile">Objects/Objects/BarrierSandbagLowCorner_1/BarrierSandbagLowCorner_1.mb</field>
		<field name="RootNode">export</field>
		<field name="LodCount">3</field>
		<field ref="systems/mesh/objectslodsettings_1/30f14f56-6d6c-4158-99d1-52467972a47f" name="LodSettings" />
		<array name="SurfaceShaders" />
		<field name="ZOnlyMesh">true</field>
		<array name="KeepZOnlyVertexElements" />
		<array name="ExcludeZOnlyMaterials" />
		<field name="StreamInstancingEnable">false</field>
		<field name="CompressPositionsEnable">true</field>
		<field name="ManualDrawOrderEnable">false</field>
		<field name="GenerateOcclusionTexture">false</field>
		<array name="CulledOcclusionTextureShaders" />
		<field name="OcclusionTextureResolution">1024</field>
		<field name="OcclusionTextureQuality">3</field>
		<field name="OcclusionMaxDistance">1.0</field>
		<field name="OcclusionContrast">1.0</field>
		<field name="OcclusionFallOff">0</field>
		<field ref="null" name="OcclusionTexture" />
		<field name="StreamingEnable">true</field>
		<field name="TangentSpaceBasisEnable">true</field>
		<field name="IrradianceVolumeEnable">false</field>
		<field name="OccluderMeshEnable">false</field>
		<field name="OccluderMeshNode" />
		<field name="HighPriorityOccluderMesh">false</field>
		<field name="Ps3EdgeEnable">true</field>
		<field name="Ps3EdgeScoreErrorWorkaroundEnable">false</field>
		<field name="Ps3SootEdgeEnable">true</field>
		<field name="Ps3SootEdgeScoreErrorWorkaroundEnable">false</field>
		<array name="ShaderSets">
			<item ref="95b3a745-d66d-11dd-b2d2-ffd259169149" />
			<item ref="fd43cbc7-f677-4e31-8453-6be5076614b0" />
		</array>
		<field name="RadiosityMesh">false</field>
		<field ref="null" name="RadiosityAlbedoTexture" />
		<field name="SootType">StDisabled</field>
		<field name="SootVoxelSize">3.0</field>
		<field name="SootSplitableTriangleEdgeLength">1.0</field>
		<field ref="null" name="Sectorization" />
		<field name="UndergrowthShadowEnable">false</field>
	</instance>
	<instance guid="95B3A745-D66D-11DD-B2D2-FFD259169149" type="Render.MeshShaderSetAsset">
		<field name="Name">Objects/Objects/BarrierSandbagLowCorner_1/BarrierSandbagLowCorner_1_Mesh</field>
		<field name="MemoryReportGroup">MemoryReportGroup_default</field>
		<array name="SurfaceShaders">
			<complex>
				<field name="Name">BarrierSandbag_Top</field>
				<field ref="objects/objects/barriersandbag_1/shaders/sandbags_top/8a5be4c5-b180-11dd-9aa9-9abececb4cb0" name="Shader" />
			</complex>
			<complex>
				<field name="Name">BarrierSandbag_Sides</field>
				<field ref="objects/objects/barriersandbag_1/shaders/sandbags_side/8a5b6f95-b180-11dd-9aa9-9abececb4cb0" name="Shader" />
			</complex>
		</array>
	</instance>
	<instance guid="FD43CBC7-F677-4E31-8453-6BE5076614B0" type="Render.MeshShaderSetAsset">
		<field name="Name">Objects/Objects/BarrierSandbagLowCorner_1/BarrierSandbagLowCorner_1_Mesh</field>
		<field name="MemoryReportGroup">MemoryReportGroup_default</field>
		<array name="SurfaceShaders">
			<complex>
				<field name="Name">BarrierSandbag_Sides</field>
				<field ref="objects/objects/barriersandbag_1/shaders/sandbags_side_green/4afa42d1-b302-4284-847d-32e22c3e8775" name="Shader" />
			</complex>
			<complex>
				<field name="Name">BarrierSandbag_Top</field>
				<field ref="objects/objects/barriersandbag_1/shaders/sandbags_top_green/614bacca-8e42-4e08-9461-0f8fb1055c00" name="Shader" />
			</complex>
		</array>
	</instance>
</partition>
