<?xml version="1.0"?>
<partition guid="F80B95C2-7CD2-4F7E-BAB2-9DC94B3E466B" primaryInstance="2610A2B6-9782-403E-A306-E01BAE53714F" exportMode="All">
	<instance guid="D9DE7484-CEC1-48BB-9D5B-23626017848F" type="Entity.EffectAsset">
		<field name="Name">Effects/Weapons/ShellEjections/Effect_ShellEjection_S_Right</field>
		<field name="MemoryReportGroup">MemoryReportGroup_default</field>
		<array name="Objects" />
		<array name="EventConnections" />
		<array name="DataConnections" />
		<field ref="null" name="Descriptor" />
		<field ref="2610a2b6-9782-403e-a306-e01bae53714f" name="Object" />
	</instance>
	<instance guid="2610A2B6-9782-403E-A306-E01BAE53714F" type="Entity.EffectEntityData" id="Effect_ShellEjection_S_Right">
		<array name="Components">
			<item ref="222769aa-4d1d-49a7-bba2-c5be1f70c760" />
			<item ref="b5e5be9a-2762-4a13-b6fe-984eeea72163" />
			<item ref="47627493-4ab5-44bd-86c8-164f3d5f755d" />
		</array>
		<field name="Enumeration">0</field>
		<field name="Name" />
		<complex name="Transform">1.0/0/0/*nonzero*/0/1.0/0/*nonzero*/0/0/1.0/*nonzero*/0/0/0/*nonzero*</complex>
		<field name="MaxInstanceCount">10</field>
		<field name="CullDistance">0</field>
		<field name="ResetInstanceWhenStarted">true</field>
		<field name="TriggerPostEffect">false</field>
		<field name="PostEffectContrastOffset">0</field>
		<complex name="PostEffectBrightnessOffset">0/0/0/*nonzero*</complex>
		<field name="PostEffectFadeInTime">0</field>
		<field name="PostEffectFadeOutTime">0</field>
		<field name="PostEffectSizeScale">1.0</field>
		<field name="PostEffectDistanceFallof">0.00999999977648</field>
	</instance>
	<instance guid="222769AA-4D1D-49A7-BBA2-C5BE1F70C760" type="Emitter.EmitterEntityData">
		<array name="Components" />
		<field name="Enumeration">0</field>
		<field name="Name" />
		<complex name="Transform">0.999999403954/0/0/*nonzero*/0/0.999999403954/0/*nonzero*/0/0/1.0/*nonzero*/0/0/0/*nonzero*</complex>
		<field name="MaxInstanceCount">30</field>
		<field name="CullDistance">0</field>
		<field name="ResetInstanceWhenStarted">true</field>
		<field name="TriggerPostEffect">false</field>
		<field name="PostEffectContrastOffset">0</field>
		<complex name="PostEffectBrightnessOffset">0/0/0/*nonzero*</complex>
		<field name="PostEffectFadeInTime">0</field>
		<field name="PostEffectFadeOutTime">0</field>
		<field name="PostEffectSizeScale">1.0</field>
		<field name="PostEffectDistanceFallof">0.00999999977648</field>
		<field name="MoveEmitterInSpiral">false</field>
		<field name="ShootEmitterFromCamera">false</field>
		<field name="SpawnCompositeMeshPart">false</field>
		<field name="CompositeMeshPartIndex">-1</field>
		<field name="StartStop">true</field>
		<field name="Pause">false</field>
		<field ref="emitters/weapons/shellejections/_emittertemplates/emittertemplate_shell_sparks_s_01/b9a60742-1817-4bbb-8422-a5ceeda7463b" name="Emitter" />
		<field name="SpawnProbability">1.0</field>
	</instance>
	<instance guid="B5E5BE9A-2762-4A13-B6FE-984EEEA72163" type="Emitter.EmitterEntityData">
		<array name="Components" />
		<field name="Enumeration">0</field>
		<field name="Name" />
		<complex name="Transform">0.999999403954/0/0/*nonzero*/0/0.999999403954/0/*nonzero*/0/0/1.0/*nonzero*/0/0/0/*nonzero*</complex>
		<field name="MaxInstanceCount">30</field>
		<field name="CullDistance">0</field>
		<field name="ResetInstanceWhenStarted">true</field>
		<field name="TriggerPostEffect">false</field>
		<field name="PostEffectContrastOffset">0</field>
		<complex name="PostEffectBrightnessOffset">0/0/0/*nonzero*</complex>
		<field name="PostEffectFadeInTime">0</field>
		<field name="PostEffectFadeOutTime">0</field>
		<field name="PostEffectSizeScale">1.0</field>
		<field name="PostEffectDistanceFallof">0.00999999977648</field>
		<field name="MoveEmitterInSpiral">false</field>
		<field name="ShootEmitterFromCamera">false</field>
		<field name="SpawnCompositeMeshPart">false</field>
		<field name="CompositeMeshPartIndex">-1</field>
		<field name="StartStop">true</field>
		<field name="Pause">false</field>
		<field ref="emitters/weapons/shellejections/_emittertemplates/emittertemplate_shell_smoke_s_01/0490c293-5361-45be-b6c7-516c44f8ffeb" name="Emitter" />
		<field name="SpawnProbability">1.0</field>
	</instance>
	<instance guid="47627493-4AB5-44BD-86C8-164F3D5F755D" type="Emitter.EmitterEntityData">
		<array name="Components" />
		<field name="Enumeration">0</field>
		<field name="Name" />
		<complex name="Transform">0.999999582767/0/0/*nonzero*/0/0.999999582767/0/*nonzero*/0/0/1.0/*nonzero*/0/0/0/*nonzero*</complex>
		<field name="MaxInstanceCount">30</field>
		<field name="CullDistance">0</field>
		<field name="ResetInstanceWhenStarted">true</field>
		<field name="TriggerPostEffect">false</field>
		<field name="PostEffectContrastOffset">0</field>
		<complex name="PostEffectBrightnessOffset">0/0/0/*nonzero*</complex>
		<field name="PostEffectFadeInTime">0</field>
		<field name="PostEffectFadeOutTime">0</field>
		<field name="PostEffectSizeScale">1.0</field>
		<field name="PostEffectDistanceFallof">0.00999999977648</field>
		<field name="MoveEmitterInSpiral">false</field>
		<field name="ShootEmitterFromCamera">false</field>
		<field name="SpawnCompositeMeshPart">false</field>
		<field name="CompositeMeshPartIndex">-1</field>
		<field name="StartStop">true</field>
		<field name="Pause">false</field>
		<field ref="emitters/weapons/shellejections/_emittertemplates/emittertemplate_shell_s_right_01/ed52a90f-f9f1-4160-bf41-124d4130713b" name="Emitter" />
		<field name="SpawnProbability">1.0</field>
	</instance>
</partition>
