<?xml version="1.0"?>
<partition guid="F2EA1764-1FB2-4D4B-BF9D-C406C251A576" primaryInstance="396BF795-4ABF-4092-959A-6D8E9FE59896" exportMode="All">
	<instance guid="139A0D1C-9C39-41D1-8286-107321F204AC" type="Emitter.EmitterDocument">
		<field name="Name">FX/Impacts/Dirt/Emitter_M/Em_Impact_Dirt_SmokeTrailChild_M_01</field>
		<field name="MemoryReportGroup">MemoryReportGroup_default</field>
		<array name="EmitterComponents">
			<item ref="1f67548c-045c-47d1-982e-1aa971780558" />
			<item ref="4454505b-d925-4778-b76b-fbfca20a7043" />
			<item ref="76e1e9f1-a2e9-4401-aae9-420226e4f953" />
			<item ref="10fdf80b-410b-46c2-aba7-2dd15bfe0f19" />
			<item ref="7cd54fe8-88d8-4e1c-bc8a-9ea823fdb782" />
			<item ref="d3dc0d1d-0373-493c-b086-7daddf6dab16" />
			<item ref="1f295c09-957b-49fc-94e9-65bd5e282380" />
			<item ref="517e02b5-3c7d-4eb4-9a5e-68dc235238d5" />
			<item ref="8ce3459d-7dfa-4aab-b28e-daddac19889e" />
			<item ref="3300169c-5837-49fc-b9d6-dec206134980" />
			<item ref="4b568ad7-9481-4343-bdd3-3e00f20f802c" />
			<item ref="73999bec-9d43-4fe3-a740-01e6a3f4a350" />
			<item ref="49fec504-0c2a-4877-bc15-29671b8e9be1" />
			<item ref="66834144-e68b-4866-84c1-15df939b2872" />
			<item ref="239ec2cd-4cf6-4749-99e5-1ac52311f445" />
			<item ref="4eca18df-ec8e-45a7-9f07-1c8b6c3933db" />
			<item ref="79ae9f70-fd71-445f-b3f6-c0d35e1d831b" />
			<item ref="15f1de9a-58c9-4317-a6c7-6b01d9aff40d" />
			<item ref="ee3f9e3e-f587-4263-a108-f2ab175cabbf" />
			<item ref="94c02feb-2ec7-4fbd-bec2-f0d20bebbe00" />
			<item ref="c091211a-91fc-4edf-a8ba-e794b874dc5f" />
			<item ref="71154b3d-d32c-43a4-870d-7f38171354b6" />
			<item ref="41c7fe4a-a9dd-4905-997d-af47a4a9b00a" />
			<item ref="5d5d2822-9d26-4ac6-8397-ea7ac4eca17f" />
			<item ref="429cba75-4fe8-48be-9644-584ad8ce3b58" />
			<item ref="9a40492e-2ab0-4eec-9995-896976604160" />
			<item ref="8f2abb62-491b-435a-bdfd-4ca67ca5eb74" />
			<item ref="9aa6f53f-145b-4b91-931e-a278b206e892" />
		</array>
		<array name="EmitterComponentConnections" />
		<array name="ProcessorConnections" />
		<field ref="1f67548c-045c-47d1-982e-1aa971780558" name="RootProcessor" />
		<field ref="396bf795-4abf-4092-959a-6d8e9fe59896" name="TemplateData" />
	</instance>
	<instance guid="396BF795-4ABF-4092-959A-6D8E9FE59896" type="Emitter.EmitterTemplateData" id="Em_Impact_Dirt_SmokeTrailChild_M_01">
		<field ref="d3dc0d1d-0373-493c-b086-7daddf6dab16" name="RootProcessor" />
		<field name="MaxCount">11</field>
		<field name="Name">FX/Impacts/Dirt/Emitter_M/Em_Impact_Dirt_SmokeTrailChild_M_01</field>
		<field name="Lifetime">0.10000000149</field>
		<field name="LifetimeFrameCount">0</field>
		<field name="FollowSpawnSource">false</field>
		<field name="KillParticlesWithEmitter">false</field>
		<field name="VisibleAfterDistance">0</field>
		<field name="OverrideScreenAreaCulling">false</field>
		<field name="EmittableType">ScreenAlignedQuad</field>
		<field ref="null" name="Mesh" />
		<array name="CompositeMeshPartNames"></array>
		<field ref="null" name="Physics" />
		<field ref="null" name="FloatPhysics" />
		<field ref="null" name="PhysicsData" />
		<field name="Emissive">false</field>
		<field name="Opaque">false</field>
		<field name="VertexPixelLightingBlendFactor">0</field>
		<field name="GlobalLocalNormalBlendFactor">1.0</field>
		<field name="AmbientLightBlendFactor">0.10000000149</field>
		<field name="AlphaAsColorBlendFactor">0.600000023842</field>
		<field name="SoftParticlesFadeDistanceMultiplier">0</field>
		<field name="ForceNiceSorting">false</field>
		<field name="LocalSpace">false</field>
		<field name="MaxDistanceForScaling">100.0</field>
		<field name="DistanceScaleMinClamp">1.0</field>
		<field name="DistanceScaleMaxClamp">2.0</field>
		<field name="ActAsPointLight">false</field>
		<complex name="PointLightColor">1.0/1.0/1.0/*zero*</complex>
		<field name="PointLightRadius">20.0</field>
		<field name="PointLightFadeStartDistance">25.0</field>
		<field name="PointLightFadeEndDistance">30.0</field>
		<complex name="PointLightPivot">0/0/0/*zero*</complex>
		<field name="PointLightRandomIntensityMin">1.0</field>
		<field name="PointLightRandomIntensityMax">1.0</field>
		<complex name="PointLightIntensity">0/0/0/1.0</complex>
		<field name="PointLightMinClamp">0</field>
		<field name="PointLightMaxClamp">1.0</field>
		<field name="ParticleCullingFactor">0.800000011921</field>
		<field name="MaxSpawnDistance">0</field>
		<field name="MinScreenArea">1.0</field>
		<field name="MeshCullingDistance">0</field>
		<field name="FreezeParticleOnSleep">false</field>
		<array name="ZOcclusionLookup"></array>
	</instance>
	<instance guid="1F67548C-045C-47D1-982E-1AA971780558" type="Emitter.UpdateAgeData">
		<field ref="null" name="Pre" />
		<field ref="null" name="Post" />
		<field name="Deprecated">false</field>
		<field ref="ee3f9e3e-f587-4263-a108-f2ab175cabbf" name="NextProcessor" />
		<field name="Edited">false</field>
		<field name="ProcessorType">PtUpdateAge</field>
		<field name="Enable">true</field>
		<field name="EvaluatorInput">EfNormTime</field>
		<field name="AcceptsEvaluator">false</field>
		<complex name="DefaultValues">1.0/1.0/1.0/1.0</complex>
		<field name="Lifetime">2.0</field>
	</instance>
	<instance guid="4454505B-D925-4778-B76B-FBFCA20A7043" type="Emitter.SpawnSpeedData">
		<field ref="10fdf80b-410b-46c2-aba7-2dd15bfe0f19" name="Pre" />
		<field ref="null" name="Post" />
		<field name="Deprecated">false</field>
		<field ref="517e02b5-3c7d-4eb4-9a5e-68dc235238d5" name="NextProcessor" />
		<field name="Edited">false</field>
		<field name="ProcessorType">PtSpawnSpeed</field>
		<field name="Enable">true</field>
		<field name="EvaluatorInput">EfNormTime</field>
		<field name="AcceptsEvaluator">true</field>
		<complex name="DefaultValues">1.0/1.0/1.0/1.0</complex>
		<field name="Speed">0.5</field>
	</instance>
	<instance guid="76E1E9F1-A2E9-4401-AAE9-420226E4F953" type="Emitter.SpawnSizeData">
		<field ref="7cd54fe8-88d8-4e1c-bc8a-9ea823fdb782" name="Pre" />
		<field ref="null" name="Post" />
		<field name="Deprecated">false</field>
		<field ref="4b568ad7-9481-4343-bdd3-3e00f20f802c" name="NextProcessor" />
		<field name="Edited">false</field>
		<field name="ProcessorType">PtSpawnSize</field>
		<field name="Enable">true</field>
		<field name="EvaluatorInput">EfNormTime</field>
		<field name="AcceptsEvaluator">true</field>
		<complex name="DefaultValues">1.0/1.0/1.0/1.0</complex>
		<field name="Size">0.800000011921</field>
	</instance>
	<instance guid="10FDF80B-410B-46C2-ABA7-2DD15BFE0F19" type="Emitter.RandomEvaluatorData">
		<field ref="null" name="Pre" />
		<field ref="null" name="Post" />
		<field name="Deprecated">false</field>
		<field name="EvaluatorType">EtRandom</field>
		<field name="EmitterParameter">EmitterParameterNone</field>
		<field name="Max">1.0</field>
		<field name="Min">-1.0</field>
	</instance>
	<instance guid="7CD54FE8-88D8-4E1C-BC8A-9EA823FDB782" type="Emitter.RandomEvaluatorData">
		<field ref="null" name="Pre" />
		<field ref="null" name="Post" />
		<field name="Deprecated">false</field>
		<field name="EvaluatorType">EtRandom</field>
		<field name="EmitterParameter">EmitterParameterNone</field>
		<field name="Max">1.0</field>
		<field name="Min">0.5</field>
	</instance>
	<instance guid="D3DC0D1D-0373-493C-B086-7DADDF6DAB16" type="Emitter.SpawnRateData">
		<field ref="null" name="Pre" />
		<field ref="null" name="Post" />
		<field name="Deprecated">false</field>
		<field ref="4454505b-d925-4778-b76b-fbfca20a7043" name="NextProcessor" />
		<field name="Edited">false</field>
		<field name="ProcessorType">PtSpawnRate</field>
		<field name="Enable">true</field>
		<field name="EvaluatorInput">EfNormTime</field>
		<field name="AcceptsEvaluator">true</field>
		<complex name="DefaultValues">1.0/1.0/1.0/1.0</complex>
		<field name="SpawnRate">100.0</field>
		<field name="TrailSegmentLength">1.0</field>
		<field name="DynamicFrequencyAreaClamp">0.800000011921</field>
		<field name="DistributeOverTime">false</field>
		<field name="DistributeOverDistance">false</field>
	</instance>
	<instance guid="1F295C09-957B-49FC-94E9-65BD5E282380" type="Emitter.SpawnDirectionData">
		<field ref="8ce3459d-7dfa-4aab-b28e-daddac19889e" name="Pre" />
		<field ref="null" name="Post" />
		<field name="Deprecated">false</field>
		<field ref="76e1e9f1-a2e9-4401-aae9-420226e4f953" name="NextProcessor" />
		<field name="Edited">false</field>
		<field name="ProcessorType">PtSpawnDirection</field>
		<field name="Enable">true</field>
		<field name="EvaluatorInput">EfNormTime</field>
		<field name="AcceptsEvaluator">true</field>
		<complex name="DefaultValues">0/1.0/0/*zero*</complex>
		<field name="WaitingForUbbe">true</field>
		<field name="InheritSpeedAndDirectionFromEmitter">false</field>
	</instance>
	<instance guid="517E02B5-3C7D-4EB4-9A5E-68DC235238D5" type="Emitter.SpawnPositionData">
		<field ref="null" name="Pre" />
		<field ref="null" name="Post" />
		<field name="Deprecated">false</field>
		<field ref="1f295c09-957b-49fc-94e9-65bd5e282380" name="NextProcessor" />
		<field name="Edited">false</field>
		<field name="ProcessorType">PtSpawnPosition</field>
		<field name="Enable">true</field>
		<field name="EvaluatorInput">EfNormTime</field>
		<field name="AcceptsEvaluator">true</field>
		<complex name="DefaultValues">0/0/0/1.0</complex>
		<field name="WaitingForUbbe">true</field>
	</instance>
	<instance guid="8CE3459D-7DFA-4AAB-B28E-DADDAC19889E" type="Emitter.RotateVectorData">
		<field ref="null" name="Pre" />
		<field ref="null" name="Post" />
		<field name="Deprecated">false</field>
		<field name="EvaluatorType">EtRotateVector</field>
		<field name="EmitterParameter">EmitterParameterNone</field>
		<field name="Angle">1.0</field>
		<field name="RotateWithinPlane">false</field>
	</instance>
	<instance guid="3300169C-5837-49FC-B9D6-DEC206134980" type="Emitter.UpdateRotationData">
		<field ref="49fec504-0c2a-4877-bc15-29671b8e9be1" name="Pre" />
		<field ref="null" name="Post" />
		<field name="Deprecated">false</field>
		<field ref="4eca18df-ec8e-45a7-9f07-1c8b6c3933db" name="NextProcessor" />
		<field name="Edited">false</field>
		<field name="ProcessorType">PtUpdateRotation</field>
		<field name="Enable">true</field>
		<field name="EvaluatorInput">EfNormTime</field>
		<field name="AcceptsEvaluator">true</field>
		<complex name="DefaultValues">1.0/0/0/*zero*</complex>
		<complex name="TextureInfo1">
			<field ref="null" name="Texture" />
			<field ref="textures/effects/emittersystem/defaultnormalmap/503e7801-e113-4f8d-abe3-e236dcf605c8" name="Normalmap" />
			<field name="AnimationFrameCount">49.0</field>
			<field name="AnimationFrameColumnCount">7.0</field>
			<field name="TextureOriginU">0</field>
			<field name="TextureOriginV">0</field>
			<field name="AnimationStepU">0</field>
			<field name="AnimationStepV">0</field>
			<field name="NmTextureOriginU">0</field>
			<field name="NmTextureOriginV">0</field>
			<field name="NmAnimationStepU">1.0</field>
			<field name="NmAnimationStepV">1.0</field>
			<field name="EnableAnimation">false</field>
		</complex>
	</instance>
	<instance guid="4B568AD7-9481-4343-BDD3-3E00F20F802C" type="Emitter.SpawnRotationData">
		<field ref="66834144-e68b-4866-84c1-15df939b2872" name="Pre" />
		<field ref="null" name="Post" />
		<field name="Deprecated">false</field>
		<field ref="73999bec-9d43-4fe3-a740-01e6a3f4a350" name="NextProcessor" />
		<field name="Edited">false</field>
		<field name="ProcessorType">PtSpawnRotation</field>
		<field name="Enable">true</field>
		<field name="EvaluatorInput">EfNormTime</field>
		<field name="AcceptsEvaluator">true</field>
		<complex name="DefaultValues">1.0/1.0/1.0/1.0</complex>
		<field name="Rotation">1.0</field>
	</instance>
	<instance guid="73999BEC-9D43-4FE3-A740-01E6A3F4A350" type="Emitter.SpawnRotationSpeedData">
		<field ref="239ec2cd-4cf6-4749-99e5-1ac52311f445" name="Pre" />
		<field ref="null" name="Post" />
		<field name="Deprecated">false</field>
		<field ref="1f67548c-045c-47d1-982e-1aa971780558" name="NextProcessor" />
		<field name="Edited">false</field>
		<field name="ProcessorType">PtSpawnRotationSpeed</field>
		<field name="Enable">true</field>
		<field name="EvaluatorInput">EfNormTime</field>
		<field name="AcceptsEvaluator">true</field>
		<complex name="DefaultValues">1.0/1.0/1.0/1.0</complex>
		<field name="RotationSpeed">0.10000000149</field>
	</instance>
	<instance guid="49FEC504-0C2A-4877-BC15-29671B8E9BE1" type="Emitter.PolynomialData">
		<field ref="null" name="Pre" />
		<field ref="null" name="Post" />
		<field name="Deprecated">false</field>
		<field name="EvaluatorType">EtPolynomial</field>
		<field name="EmitterParameter">EmitterParameterNone</field>
		<complex name="Coefficients">0/0.985067605972/-1.99846029282/1.00446438789</complex>
		<field name="ScaleValue">1.0</field>
		<field name="MinClamp">0</field>
		<field name="MaxClamp">1.0</field>
	</instance>
	<instance guid="66834144-E68B-4866-84C1-15DF939B2872" type="Emitter.RandomEvaluatorData">
		<field ref="null" name="Pre" />
		<field ref="null" name="Post" />
		<field name="Deprecated">false</field>
		<field name="EvaluatorType">EtRandom</field>
		<field name="EmitterParameter">EmitterParameterNone</field>
		<field name="Max">45.0</field>
		<field name="Min">-45.0</field>
	</instance>
	<instance guid="239EC2CD-4CF6-4749-99E5-1AC52311F445" type="Emitter.RandomEvaluatorData">
		<field ref="null" name="Pre" />
		<field ref="null" name="Post" />
		<field name="Deprecated">false</field>
		<field name="EvaluatorType">EtRandom</field>
		<field name="EmitterParameter">EmitterParameterNone</field>
		<field name="Max">1.0</field>
		<field name="Min">-1.0</field>
	</instance>
	<instance guid="4ECA18DF-EC8E-45A7-9F07-1C8B6C3933DB" type="Emitter.UpdateSizeData">
		<field ref="79ae9f70-fd71-445f-b3f6-c0d35e1d831b" name="Pre" />
		<field ref="null" name="Post" />
		<field name="Deprecated">false</field>
		<field ref="c091211a-91fc-4edf-a8ba-e794b874dc5f" name="NextProcessor" />
		<field name="Edited">false</field>
		<field name="ProcessorType">PtUpdateSize</field>
		<field name="Enable">true</field>
		<field name="EvaluatorInput">EfNormTime</field>
		<field name="AcceptsEvaluator">true</field>
		<complex name="DefaultValues">1.0/1.0/1.0/1.0</complex>
		<complex name="Pivot">0/0</complex>
	</instance>
	<instance guid="79AE9F70-FD71-445F-B3F6-C0D35E1D831B" type="Emitter.PolynomialData">
		<field ref="null" name="Pre" />
		<field ref="null" name="Post" />
		<field name="Deprecated">false</field>
		<field name="EvaluatorType">EtPolynomial</field>
		<field name="EmitterParameter">EmitterParameterNone</field>
		<complex name="Coefficients">-0.209285497665/-0.143248558044/1.00031375885/0.355164587498</complex>
		<field name="ScaleValue">0</field>
		<field name="MinClamp">0</field>
		<field name="MaxClamp">1.0</field>
	</instance>
	<instance guid="15F1DE9A-58C9-4317-A6C7-6B01D9AFF40D" type="Emitter.AirResistanceData">
		<field ref="null" name="Pre" />
		<field ref="null" name="Post" />
		<field name="Deprecated">false</field>
		<field ref="21b7fd07-4f1a-11e0-bef3-9e12707b7abb" name="NextProcessor" />
		<field name="Edited">false</field>
		<field name="ProcessorType">PtAirResistance</field>
		<field name="Enable">true</field>
		<field name="EvaluatorInput">EfNormTime</field>
		<field name="AcceptsEvaluator">true</field>
		<complex name="DefaultValues">1.0/1.0/1.0/1.0</complex>
		<field name="DragFactor">15.0</field>
	</instance>
	<instance guid="EE3F9E3E-F587-4263-A108-F2AB175CABBF" type="Emitter.GravityData">
		<field ref="null" name="Pre" />
		<field ref="null" name="Post" />
		<field name="Deprecated">false</field>
		<field ref="15f1de9a-58c9-4317-a6c7-6b01d9aff40d" name="NextProcessor" />
		<field name="Edited">false</field>
		<field name="ProcessorType">PtGravity</field>
		<field name="Enable">true</field>
		<field name="EvaluatorInput">EfNormTime</field>
		<field name="AcceptsEvaluator">true</field>
		<complex name="DefaultValues">1.0/1.0/1.0/1.0</complex>
		<field name="Gravity">-10.0</field>
	</instance>
	<instance guid="94C02FEB-2EC7-4FBD-BEC2-F0D20BEBBE00" type="Emitter.UpdateAlphaLevelScaleData">
		<field ref="429cba75-4fe8-48be-9644-584ad8ce3b58" name="Pre" />
		<field ref="null" name="Post" />
		<field name="Deprecated">false</field>
		<field ref="21b7fd06-4f1a-11e0-bef3-9e12707b7abb" name="NextProcessor" />
		<field name="Edited">false</field>
		<field name="ProcessorType">PtUpdateAlphaLevelScale</field>
		<field name="Enable">true</field>
		<field name="EvaluatorInput">EfNormTime</field>
		<field name="AcceptsEvaluator">true</field>
		<complex name="DefaultValues">1.0/1.0/1.0/1.0</complex>
		<field name="Exponent">10.0</field>
	</instance>
	<instance guid="C091211A-91FC-4EDF-A8BA-E794B874DC5F" type="Emitter.UpdateAlphaLevelMaxData">
		<field ref="9a40492e-2ab0-4eec-9995-896976604160" name="Pre" />
		<field ref="null" name="Post" />
		<field name="Deprecated">false</field>
		<field ref="94c02feb-2ec7-4fbd-bec2-f0d20bebbe00" name="NextProcessor" />
		<field name="Edited">false</field>
		<field name="ProcessorType">PtUpdateAlphaLevelMax</field>
		<field name="Enable">true</field>
		<field name="EvaluatorInput">EfNormTime</field>
		<field name="AcceptsEvaluator">true</field>
		<complex name="DefaultValues">1.0/1.0/1.0/1.0</complex>
		<field name="MaxLevel">1.0</field>
	</instance>
	<instance guid="71154B3D-D32C-43A4-870D-7F38171354B6" type="Emitter.UpdateColorData">
		<field ref="8f2abb62-491b-435a-bdfd-4ca67ca5eb74" name="Pre" />
		<field ref="null" name="Post" />
		<field name="Deprecated">false</field>
		<field ref="5d5d2822-9d26-4ac6-8397-ea7ac4eca17f" name="NextProcessor" />
		<field name="Edited">false</field>
		<field name="ProcessorType">PtUpdateColor</field>
		<field name="Enable">true</field>
		<field name="EvaluatorInput">EfNormTime</field>
		<field name="AcceptsEvaluator">true</field>
		<complex name="DefaultValues">0.144999995828/0.133000001311/0.120999999344/1.0</complex>
		<complex name="Color">0.144999995828/0.133000001311/0.120999999344/*nonzero*</complex>
	</instance>
	<instance guid="41C7FE4A-A9DD-4905-997D-AF47A4A9B00A" type="Emitter.UpdateTextureCoordsData">
		<field ref="null" name="Pre" />
		<field ref="null" name="Post" />
		<field name="Deprecated">false</field>
		<field ref="3300169c-5837-49fc-b9d6-dec206134980" name="NextProcessor" />
		<field name="Edited">false</field>
		<field name="ProcessorType">PtUpdateTextureCoords</field>
		<field name="Enable">true</field>
		<field name="EvaluatorInput">EfNormTime</field>
		<field name="AcceptsEvaluator">true</field>
		<complex name="DefaultValues">1.0/0/0/*zero*</complex>
		<complex name="TextureInfo1">
			<field ref="textures/effects/smoke/smokesoft_04_c/0c62fa1e-7f02-43aa-bba4-b59b0455cfd1" name="Texture" />
			<field ref="textures/effects/emittersystem/defaultnormalmap/503e7801-e113-4f8d-abe3-e236dcf605c8" name="Normalmap" />
			<field name="AnimationFrameCount">4.0</field>
			<field name="AnimationFrameColumnCount">2.0</field>
			<field name="TextureOriginU">0.78271484375</field>
			<field name="TextureOriginV">0.00146484375</field>
			<field name="AnimationStepU">0.0283203125</field>
			<field name="AnimationStepV">0.0283203125</field>
			<field name="NmTextureOriginU">0.7529296875</field>
			<field name="NmTextureOriginV">0.380859375</field>
			<field name="NmAnimationStepU">-0.0048828125</field>
			<field name="NmAnimationStepV">-0.009765625</field>
			<field name="EnableAnimation">false</field>
		</complex>
		<field name="TextureBlendValue">1.0</field>
	</instance>
	<instance guid="5D5D2822-9D26-4AC6-8397-EA7AC4ECA17F" type="Emitter.UpdateTransparencyData">
		<field ref="9aa6f53f-145b-4b91-931e-a278b206e892" name="Pre" />
		<field ref="null" name="Post" />
		<field name="Deprecated">false</field>
		<field ref="41c7fe4a-a9dd-4905-997d-af47a4a9b00a" name="NextProcessor" />
		<field name="Edited">false</field>
		<field name="ProcessorType">PtUpdateTransparency</field>
		<field name="Enable">true</field>
		<field name="EvaluatorInput">EfNormTime</field>
		<field name="AcceptsEvaluator">true</field>
		<complex name="DefaultValues">1.0/1.0/1.0/1.0</complex>
		<field name="CullThreshold">0.20000000298</field>
	</instance>
	<instance guid="429CBA75-4FE8-48BE-9644-584AD8CE3B58" type="Emitter.PolynomialData">
		<field ref="null" name="Pre" />
		<field ref="null" name="Post" />
		<field name="Deprecated">false</field>
		<field name="EvaluatorType">EtPolynomial</field>
		<field name="EmitterParameter">EmitterParameterNone</field>
		<complex name="Coefficients">-0.162920176983/1.36507642269/-0.254675388336/0.0391677543521</complex>
		<field name="ScaleValue">1.0</field>
		<field name="MinClamp">0.10000000149</field>
		<field name="MaxClamp">0.990000009537</field>
	</instance>
	<instance guid="9A40492E-2AB0-4EEC-9995-896976604160" type="Emitter.PolynomialData">
		<field ref="null" name="Pre" />
		<field ref="null" name="Post" />
		<field name="Deprecated">false</field>
		<field name="EvaluatorType">EtPolynomial</field>
		<field name="EmitterParameter">EmitterParameterNone</field>
		<complex name="Coefficients">0.448957443237/-0.844715118408/0.667465925217/0.747681736946</complex>
		<field name="ScaleValue">1.0</field>
		<field name="MinClamp">0</field>
		<field name="MaxClamp">1.0</field>
	</instance>
	<instance guid="8F2ABB62-491B-435A-BDFD-4CA67CA5EB74" type="Emitter.PolynomialColorInterpData">
		<field ref="null" name="Pre" />
		<field ref="null" name="Post" />
		<field name="Deprecated">false</field>
		<field name="EvaluatorType">EtPolynomialColorInterp</field>
		<field name="EmitterParameter">EmitterParameterNone</field>
		<complex name="Color0">0.0240000002086/0.0219999998808/0.019999999553/*nonzero*</complex>
		<complex name="Color1">0.620000004768/0.561999976635/0.449999988079/*nonzero*</complex>
		<complex name="Coefficients">0/0.896637916565/-1.91665220261/1.01746726036</complex>
	</instance>
	<instance guid="9AA6F53F-145B-4B91-931E-A278B206E892" type="Emitter.PolynomialData">
		<field ref="null" name="Pre" />
		<field ref="null" name="Post" />
		<field name="Deprecated">false</field>
		<field name="EvaluatorType">EtPolynomial</field>
		<field name="EmitterParameter">EmitterParameterNone</field>
		<complex name="Coefficients">0/2.14146280289/-4.15047836304/2.01578593254</complex>
		<field name="ScaleValue">0.600000023842</field>
		<field name="MinClamp">0</field>
		<field name="MaxClamp">1.0</field>
	</instance>
	<instance guid="21B7FD07-4F1A-11E0-BEF3-9E12707B7ABB" type="Emitter.UpdateLinearVelocityData">
		<field ref="null" name="Pre" />
		<field ref="null" name="Post" />
		<field name="Deprecated">false</field>
		<field ref="21b7fcec-4f1a-11e0-bef3-9e12707b7abb" name="NextProcessor" />
		<field name="Edited">false</field>
		<field name="ProcessorType">PtUpdateLinearVelocity</field>
		<field name="Enable">true</field>
		<field name="EvaluatorInput">EfNormTime</field>
		<field name="AcceptsEvaluator">true</field>
		<complex name="DefaultValues">1.0/1.0/1.0/1.0</complex>
		<field name="WaitingForUbbe">true</field>
	</instance>
	<instance guid="21B7FD06-4F1A-11E0-BEF3-9E12707B7ABB" type="Emitter.UpdateClipScaleData">
		<field ref="null" name="Pre" />
		<field ref="null" name="Post" />
		<field name="Deprecated">false</field>
		<field ref="null" name="NextProcessor" />
		<field name="Edited">false</field>
		<field name="ProcessorType">PtUpdateClipScale</field>
		<field name="Enable">true</field>
		<field name="EvaluatorInput">EfNormTime</field>
		<field name="AcceptsEvaluator">true</field>
		<complex name="DefaultValues">1.0/1.0/1.0/1.0</complex>
		<array name="Lookup">1.0/1.0/1.0/1.0/0.859375/0.9140625/0.9140625/0.921875/0.859375/0.9140625/0.9140625/0.921875/0.859375/0.9140625/0.9140625/0.921875/0.859375/0.9140625/0.9140625/0.921875/0.859375/0.9140625/0.9140625/0.921875/0.859375/0.9140625/0.9140625/0.921875/0.859375/0.9140625/0.9140625/0.921875/0.859375/0.9140625/0.9140625/0.921875/0.859375/0.9140625/0.9140625/0.921875/0.859375/0.9140625/0.9140625/0.921875/0.859375/0.9140625/0.9140625/0.921875/0.859375/0.9140625/0.9140625/0.921875/0.859375/0.9140625/0.9140625/0.921875/0.859375/0.9140625/0.9140625/0.921875/0.7890625/0.8125/0.84375/0.859375/0.765625/0.78125/0.8203125/0.828125/0.7421875/0.7734375/0.7890625/0.796875/0.7265625/0.765625/0.765625/0.765625/0.7109375/0.7578125/0.7578125/0.7421875/0.6796875/0.75/0.734375/0.7265625/0.6640625/0.7421875/0.7109375/0.703125/0.6484375/0.7265625/0.703125/0.6796875/0.625/0.703125/0.6953125/0.6640625/0.6171875/0.6953125/0.671875/0.6328125/0.59375/0.6953125/0.6640625/0.5859375/0.578125/0.6796875/0.6484375/0.5546875/0.5390625/0.671875/0.625/0.4921875/0.5234375/0.6640625/0.5703125/0.4296875/0.4375/0.6328125/0.5625/0.3515625/0.390625/0.6171875/0.484375/0.3046875/0.2578125/0.6015625/0.40625/0.21875/0.2578125/0.546875/0.390625/0.21875</array>
	</instance>
	<instance guid="21B7FCEC-4F1A-11E0-BEF3-9E12707B7ABB" type="Emitter.UpdateOrientationData">
		<field ref="null" name="Pre" />
		<field ref="null" name="Post" />
		<field name="Deprecated">false</field>
		<field ref="21b7fd08-4f1a-11e0-bef3-9e12707b7abb" name="NextProcessor" />
		<field name="Edited">false</field>
		<field name="ProcessorType">PtUpdateOrientation</field>
		<field name="Enable">true</field>
		<field name="EvaluatorInput">EfNormTime</field>
		<field name="AcceptsEvaluator">true</field>
		<complex name="DefaultValues">1.0/1.0/1.0/1.0</complex>
		<field name="WaitingForUbbe">true</field>
	</instance>
	<instance guid="21B7FD08-4F1A-11E0-BEF3-9E12707B7ABB" type="Emitter.UpdateBoundingBoxData">
		<field ref="null" name="Pre" />
		<field ref="null" name="Post" />
		<field name="Deprecated">false</field>
		<field ref="71154b3d-d32c-43a4-870d-7f38171354b6" name="NextProcessor" />
		<field name="Edited">false</field>
		<field name="ProcessorType">PtUpdateBoundingBox</field>
		<field name="Enable">true</field>
		<field name="EvaluatorInput">EfNormTime</field>
		<field name="AcceptsEvaluator">true</field>
		<complex name="DefaultValues">1.0/1.0/1.0/1.0</complex>
		<field name="WaitingForUbbe">true</field>
	</instance>
</partition>
